{
  "experiment": "det2_recheck_phase2",
  "verdict": "PASS",
  "cv_thresholds": {
    "regular_or_low_budget": 0.1,
    "irregular_high_budget": 0.25
  },
  "n_seeds": 20,
  "space_types": [
    "scalar_grid",
    "vector_grid",
    "irregular_graph",
    "tree_hierarchy"
  ],
  "budget_levels": {
    "low": 0.1,
    "high": 0.3
  },
  "n_total_runs": 160,
  "elapsed_s": 3.45,
  "cells": [
    {
      "space": "scalar_grid",
      "budget": "low",
      "pass": true,
      "cv_threshold": 0.1,
      "max_cv": 0.0,
      "metrics": {
        "n_refined": {
          "mean": 6.0,
          "std": 0.0,
          "cv": 0.0,
          "kill_criteria": true
        },
        "compliance": {
          "mean": 1.0,
          "std": 0.0,
          "cv": 0.0,
          "kill_criteria": true
        },
        "n_passed": {
          "mean": 6.0,
          "std": 0.0,
          "cv": 0.0,
          "kill_criteria": false
        },
        "n_rejected": {
          "mean": 0.0,
          "std": 0.0,
          "cv": 0.0,
          "kill_criteria": false
        },
        "reject_rate": {
          "mean": 0.0,
          "std": 0.0,
          "cv": 0.0,
          "kill_criteria": false
        },
        "psnr_gain": {
          "mean": 2.669435,
          "std": 0.528489,
          "cv": 0.197978,
          "kill_criteria": false
        }
      },
      "topo_metrics": null
    },
    {
      "space": "scalar_grid",
      "budget": "high",
      "pass": true,
      "cv_threshold": 0.1,
      "max_cv": 0.0,
      "metrics": {
        "n_refined": {
          "mean": 19.0,
          "std": 0.0,
          "cv": 0.0,
          "kill_criteria": true
        },
        "compliance": {
          "mean": 1.0,
          "std": 0.0,
          "cv": 0.0,
          "kill_criteria": true
        },
        "n_passed": {
          "mean": 19.0,
          "std": 0.0,
          "cv": 0.0,
          "kill_criteria": false
        },
        "n_rejected": {
          "mean": 0.0,
          "std": 0.0,
          "cv": 0.0,
          "kill_criteria": false
        },
        "reject_rate": {
          "mean": 0.0,
          "std": 0.0,
          "cv": 0.0,
          "kill_criteria": false
        },
        "psnr_gain": {
          "mean": 7.479179,
          "std": 1.220532,
          "cv": 0.163191,
          "kill_criteria": false
        }
      },
      "topo_metrics": null
    },
    {
      "space": "vector_grid",
      "budget": "low",
      "pass": true,
      "cv_threshold": 0.1,
      "max_cv": 0.0,
      "metrics": {
        "n_refined": {
          "mean": 1.0,
          "std": 0.0,
          "cv": 0.0,
          "kill_criteria": true
        },
        "compliance": {
          "mean": 1.0,
          "std": 0.0,
          "cv": 0.0,
          "kill_criteria": true
        },
        "n_passed": {
          "mean": 1.0,
          "std": 0.0,
          "cv": 0.0,
          "kill_criteria": false
        },
        "n_rejected": {
          "mean": 0.0,
          "std": 0.0,
          "cv": 0.0,
          "kill_criteria": false
        },
        "reject_rate": {
          "mean": 0.0,
          "std": 0.0,
          "cv": 0.0,
          "kill_criteria": false
        },
        "psnr_gain": {
          "mean": 0.385219,
          "std": 0.068166,
          "cv": 0.176955,
          "kill_criteria": false
        }
      },
      "topo_metrics": null
    },
    {
      "space": "vector_grid",
      "budget": "high",
      "pass": true,
      "cv_threshold": 0.1,
      "max_cv": 0.0,
      "metrics": {
        "n_refined": {
          "mean": 4.0,
          "std": 0.0,
          "cv": 0.0,
          "kill_criteria": true
        },
        "compliance": {
          "mean": 1.0,
          "std": 0.0,
          "cv": 0.0,
          "kill_criteria": true
        },
        "n_passed": {
          "mean": 4.0,
          "std": 0.0,
          "cv": 0.0,
          "kill_criteria": false
        },
        "n_rejected": {
          "mean": 0.0,
          "std": 0.0,
          "cv": 0.0,
          "kill_criteria": false
        },
        "reject_rate": {
          "mean": 0.0,
          "std": 0.0,
          "cv": 0.0,
          "kill_criteria": false
        },
        "psnr_gain": {
          "mean": 1.490148,
          "std": 0.136265,
          "cv": 0.091444,
          "kill_criteria": false
        }
      },
      "topo_metrics": null
    },
    {
      "space": "irregular_graph",
      "budget": "low",
      "pass": true,
      "cv_threshold": 0.1,
      "max_cv": 0.0,
      "metrics": {
        "n_refined": {
          "mean": 1.0,
          "std": 0.0,
          "cv": 0.0,
          "kill_criteria": true
        },
        "compliance": {
          "mean": 1.0,
          "std": 0.0,
          "cv": 0.0,
          "kill_criteria": true
        },
        "n_passed": {
          "mean": 0.95,
          "std": 0.217945,
          "cv": 0.229416,
          "kill_criteria": false
        },
        "n_rejected": {
          "mean": 0.0,
          "std": 0.0,
          "cv": 0.0,
          "kill_criteria": false
        },
        "reject_rate": {
          "mean": 0.0,
          "std": 0.0,
          "cv": 0.0,
          "kill_criteria": false
        },
        "psnr_gain": {
          "mean": 1.352237,
          "std": 0.497434,
          "cv": 0.36786,
          "kill_criteria": false
        }
      },
      "topo_metrics": {
        "topo_eta_f": {
          "mean": 1.0557,
          "std": 0.0311,
          "cv": 0.0295
        },
        "topo_computation_ms": {
          "mean": 56.6598,
          "std": 4.0933,
          "cv": 0.0722
        }
      }
    },
    {
      "space": "irregular_graph",
      "budget": "high",
      "pass": true,
      "cv_threshold": 0.25,
      "max_cv": 0.096774,
      "metrics": {
        "n_refined": {
          "mean": 3.1,
          "std": 0.3,
          "cv": 0.096774,
          "kill_criteria": true
        },
        "compliance": {
          "mean": 1.0,
          "std": 0.0,
          "cv": 0.0,
          "kill_criteria": true
        },
        "n_passed": {
          "mean": 2.9,
          "std": 0.6245,
          "cv": 0.215345,
          "kill_criteria": false
        },
        "n_rejected": {
          "mean": 0.0,
          "std": 0.0,
          "cv": 0.0,
          "kill_criteria": false
        },
        "reject_rate": {
          "mean": 0.0,
          "std": 0.0,
          "cv": 0.0,
          "kill_criteria": false
        },
        "psnr_gain": {
          "mean": 3.469325,
          "std": 0.786187,
          "cv": 0.226611,
          "kill_criteria": false
        }
      },
      "topo_metrics": {
        "topo_eta_f": {
          "mean": 1.0557,
          "std": 0.0311,
          "cv": 0.0295
        },
        "topo_computation_ms": {
          "mean": 56.3086,
          "std": 2.7679,
          "cv": 0.0492
        }
      }
    },
    {
      "space": "tree_hierarchy",
      "budget": "low",
      "pass": true,
      "cv_threshold": 0.1,
      "max_cv": 0.0,
      "metrics": {
        "n_refined": {
          "mean": 1.0,
          "std": 0.0,
          "cv": 0.0,
          "kill_criteria": true
        },
        "compliance": {
          "mean": 1.0,
          "std": 0.0,
          "cv": 0.0,
          "kill_criteria": true
        },
        "n_passed": {
          "mean": 0.95,
          "std": 0.217945,
          "cv": 0.229416,
          "kill_criteria": false
        },
        "n_rejected": {
          "mean": 0.0,
          "std": 0.0,
          "cv": 0.0,
          "kill_criteria": false
        },
        "reject_rate": {
          "mean": 0.0,
          "std": 0.0,
          "cv": 0.0,
          "kill_criteria": false
        },
        "psnr_gain": {
          "mean": 1.203698,
          "std": 0.186639,
          "cv": 0.155055,
          "kill_criteria": false
        }
      },
      "topo_metrics": null
    },
    {
      "space": "tree_hierarchy",
      "budget": "high",
      "pass": true,
      "cv_threshold": 0.25,
      "max_cv": 0.0,
      "metrics": {
        "n_refined": {
          "mean": 2.0,
          "std": 0.0,
          "cv": 0.0,
          "kill_criteria": true
        },
        "compliance": {
          "mean": 1.0,
          "std": 0.0,
          "cv": 0.0,
          "kill_criteria": true
        },
        "n_passed": {
          "mean": 1.45,
          "std": 0.497494,
          "cv": 0.343099,
          "kill_criteria": false
        },
        "n_rejected": {
          "mean": 0.0,
          "std": 0.0,
          "cv": 0.0,
          "kill_criteria": false
        },
        "reject_rate": {
          "mean": 0.0,
          "std": 0.0,
          "cv": 0.0,
          "kill_criteria": false
        },
        "psnr_gain": {
          "mean": 2.236673,
          "std": 0.203667,
          "cv": 0.091058,
          "kill_criteria": false
        }
      },
      "topo_metrics": null
    }
  ],
  "raw": [
    {
      "space": "scalar_grid",
      "budget": "low",
      "budget_frac": 0.1,
      "seed": 0,
      "n_refined": 6.0,
      "n_passed": 6.0,
      "n_rejected": 0.0,
      "reject_rate": 0.0,
      "psnr_gain": 3.662296143431199,
      "compliance": 1.0,
      "topo_eta_f": 0.0,
      "topo_computation_ms": 0.0
    },
    {
      "space": "scalar_grid",
      "budget": "low",
      "budget_frac": 0.1,
      "seed": 1,
      "n_refined": 6.0,
      "n_passed": 6.0,
      "n_rejected": 0.0,
      "reject_rate": 0.0,
      "psnr_gain": 2.8537739429091182,
      "compliance": 1.0,
      "topo_eta_f": 0.0,
      "topo_computation_ms": 0.0
    },
    {
      "space": "scalar_grid",
      "budget": "low",
      "budget_frac": 0.1,
      "seed": 2,
      "n_refined": 6.0,
      "n_passed": 6.0,
      "n_rejected": 0.0,
      "reject_rate": 0.0,
      "psnr_gain": 2.7014393583533973,
      "compliance": 1.0,
      "topo_eta_f": 0.0,
      "topo_computation_ms": 0.0
    },
    {
      "space": "scalar_grid",
      "budget": "low",
      "budget_frac": 0.1,
      "seed": 3,
      "n_refined": 6.0,
      "n_passed": 6.0,
      "n_rejected": 0.0,
      "reject_rate": 0.0,
      "psnr_gain": 1.8477708730938396,
      "compliance": 1.0,
      "topo_eta_f": 0.0,
      "topo_computation_ms": 0.0
    },
    {
      "space": "scalar_grid",
      "budget": "low",
      "budget_frac": 0.1,
      "seed": 4,
      "n_refined": 6.0,
      "n_passed": 6.0,
      "n_rejected": 0.0,
      "reject_rate": 0.0,
      "psnr_gain": 2.5250364669593957,
      "compliance": 1.0,
      "topo_eta_f": 0.0,
      "topo_computation_ms": 0.0
    },
    {
      "space": "scalar_grid",
      "budget": "low",
      "budget_frac": 0.1,
      "seed": 5,
      "n_refined": 6.0,
      "n_passed": 6.0,
      "n_rejected": 0.0,
      "reject_rate": 0.0,
      "psnr_gain": 2.578934434220937,
      "compliance": 1.0,
      "topo_eta_f": 0.0,
      "topo_computation_ms": 0.0
    },
    {
      "space": "scalar_grid",
      "budget": "low",
      "budget_frac": 0.1,
      "seed": 6,
      "n_refined": 6.0,
      "n_passed": 6.0,
      "n_rejected": 0.0,
      "reject_rate": 0.0,
      "psnr_gain": 3.5060802487917755,
      "compliance": 1.0,
      "topo_eta_f": 0.0,
      "topo_computation_ms": 0.0
    },
    {
      "space": "scalar_grid",
      "budget": "low",
      "budget_frac": 0.1,
      "seed": 7,
      "n_refined": 6.0,
      "n_passed": 6.0,
      "n_rejected": 0.0,
      "reject_rate": 0.0,
      "psnr_gain": 2.472742725897362,
      "compliance": 1.0,
      "topo_eta_f": 0.0,
      "topo_computation_ms": 0.0
    },
    {
      "space": "scalar_grid",
      "budget": "low",
      "budget_frac": 0.1,
      "seed": 8,
      "n_refined": 6.0,
      "n_passed": 6.0,
      "n_rejected": 0.0,
      "reject_rate": 0.0,
      "psnr_gain": 1.8315993342801704,
      "compliance": 1.0,
      "topo_eta_f": 0.0,
      "topo_computation_ms": 0.0
    },
    {
      "space": "scalar_grid",
      "budget": "low",
      "budget_frac": 0.1,
      "seed": 9,
      "n_refined": 6.0,
      "n_passed": 6.0,
      "n_rejected": 0.0,
      "reject_rate": 0.0,
      "psnr_gain": 2.4406874751638448,
      "compliance": 1.0,
      "topo_eta_f": 0.0,
      "topo_computation_ms": 0.0
    },
    {
      "space": "scalar_grid",
      "budget": "low",
      "budget_frac": 0.1,
      "seed": 10,
      "n_refined": 6.0,
      "n_passed": 6.0,
      "n_rejected": 0.0,
      "reject_rate": 0.0,
      "psnr_gain": 2.402798536218935,
      "compliance": 1.0,
      "topo_eta_f": 0.0,
      "topo_computation_ms": 0.0
    },
    {
      "space": "scalar_grid",
      "budget": "low",
      "budget_frac": 0.1,
      "seed": 11,
      "n_refined": 6.0,
      "n_passed": 6.0,
      "n_rejected": 0.0,
      "reject_rate": 0.0,
      "psnr_gain": 3.864668491737401,
      "compliance": 1.0,
      "topo_eta_f": 0.0,
      "topo_computation_ms": 0.0
    },
    {
      "space": "scalar_grid",
      "budget": "low",
      "budget_frac": 0.1,
      "seed": 12,
      "n_refined": 6.0,
      "n_passed": 6.0,
      "n_rejected": 0.0,
      "reject_rate": 0.0,
      "psnr_gain": 2.1971282018698908,
      "compliance": 1.0,
      "topo_eta_f": 0.0,
      "topo_computation_ms": 0.0
    },
    {
      "space": "scalar_grid",
      "budget": "low",
      "budget_frac": 0.1,
      "seed": 13,
      "n_refined": 6.0,
      "n_passed": 6.0,
      "n_rejected": 0.0,
      "reject_rate": 0.0,
      "psnr_gain": 2.4018953487428902,
      "compliance": 1.0,
      "topo_eta_f": 0.0,
      "topo_computation_ms": 0.0
    },
    {
      "space": "scalar_grid",
      "budget": "low",
      "budget_frac": 0.1,
      "seed": 14,
      "n_refined": 6.0,
      "n_passed": 6.0,
      "n_rejected": 0.0,
      "reject_rate": 0.0,
      "psnr_gain": 2.685833551162567,
      "compliance": 1.0,
      "topo_eta_f": 0.0,
      "topo_computation_ms": 0.0
    },
    {
      "space": "scalar_grid",
      "budget": "low",
      "budget_frac": 0.1,
      "seed": 15,
      "n_refined": 6.0,
      "n_passed": 6.0,
      "n_rejected": 0.0,
      "reject_rate": 0.0,
      "psnr_gain": 2.945137357480842,
      "compliance": 1.0,
      "topo_eta_f": 0.0,
      "topo_computation_ms": 0.0
    },
    {
      "space": "scalar_grid",
      "budget": "low",
      "budget_frac": 0.1,
      "seed": 16,
      "n_refined": 6.0,
      "n_passed": 6.0,
      "n_rejected": 0.0,
      "reject_rate": 0.0,
      "psnr_gain": 2.584067609871795,
      "compliance": 1.0,
      "topo_eta_f": 0.0,
      "topo_computation_ms": 0.0
    },
    {
      "space": "scalar_grid",
      "budget": "low",
      "budget_frac": 0.1,
      "seed": 17,
      "n_refined": 6.0,
      "n_passed": 6.0,
      "n_rejected": 0.0,
      "reject_rate": 0.0,
      "psnr_gain": 3.1809395540613217,
      "compliance": 1.0,
      "topo_eta_f": 0.0,
      "topo_computation_ms": 0.0
    },
    {
      "space": "scalar_grid",
      "budget": "low",
      "budget_frac": 0.1,
      "seed": 18,
      "n_refined": 6.0,
      "n_passed": 6.0,
      "n_rejected": 0.0,
      "reject_rate": 0.0,
      "psnr_gain": 2.471756508723505,
      "compliance": 1.0,
      "topo_eta_f": 0.0,
      "topo_computation_ms": 0.0
    },
    {
      "space": "scalar_grid",
      "budget": "low",
      "budget_frac": 0.1,
      "seed": 19,
      "n_refined": 6.0,
      "n_passed": 6.0,
      "n_rejected": 0.0,
      "reject_rate": 0.0,
      "psnr_gain": 2.23412117029563,
      "compliance": 1.0,
      "topo_eta_f": 0.0,
      "topo_computation_ms": 0.0
    },
    {
      "space": "scalar_grid",
      "budget": "high",
      "budget_frac": 0.3,
      "seed": 0,
      "n_refined": 19.0,
      "n_passed": 19.0,
      "n_rejected": 0.0,
      "reject_rate": 0.0,
      "psnr_gain": 9.820311958435589,
      "compliance": 1.0,
      "topo_eta_f": 0.0,
      "topo_computation_ms": 0.0
    },
    {
      "space": "scalar_grid",
      "budget": "high",
      "budget_frac": 0.3,
      "seed": 1,
      "n_refined": 19.0,
      "n_passed": 19.0,
      "n_rejected": 0.0,
      "reject_rate": 0.0,
      "psnr_gain": 7.664138459176222,
      "compliance": 1.0,
      "topo_eta_f": 0.0,
      "topo_computation_ms": 0.0
    },
    {
      "space": "scalar_grid",
      "budget": "high",
      "budget_frac": 0.3,
      "seed": 2,
      "n_refined": 19.0,
      "n_passed": 19.0,
      "n_rejected": 0.0,
      "reject_rate": 0.0,
      "psnr_gain": 8.534667997785839,
      "compliance": 1.0,
      "topo_eta_f": 0.0,
      "topo_computation_ms": 0.0
    },
    {
      "space": "scalar_grid",
      "budget": "high",
      "budget_frac": 0.3,
      "seed": 3,
      "n_refined": 19.0,
      "n_passed": 19.0,
      "n_rejected": 0.0,
      "reject_rate": 0.0,
      "psnr_gain": 5.996253692454118,
      "compliance": 1.0,
      "topo_eta_f": 0.0,
      "topo_computation_ms": 0.0
    },
    {
      "space": "scalar_grid",
      "budget": "high",
      "budget_frac": 0.3,
      "seed": 4,
      "n_refined": 19.0,
      "n_passed": 19.0,
      "n_rejected": 0.0,
      "reject_rate": 0.0,
      "psnr_gain": 6.758013021580972,
      "compliance": 1.0,
      "topo_eta_f": 0.0,
      "topo_computation_ms": 0.0
    },
    {
      "space": "scalar_grid",
      "budget": "high",
      "budget_frac": 0.3,
      "seed": 5,
      "n_refined": 19.0,
      "n_passed": 19.0,
      "n_rejected": 0.0,
      "reject_rate": 0.0,
      "psnr_gain": 6.911020186686798,
      "compliance": 1.0,
      "topo_eta_f": 0.0,
      "topo_computation_ms": 0.0
    },
    {
      "space": "scalar_grid",
      "budget": "high",
      "budget_frac": 0.3,
      "seed": 6,
      "n_refined": 19.0,
      "n_passed": 19.0,
      "n_rejected": 0.0,
      "reject_rate": 0.0,
      "psnr_gain": 7.382527087525368,
      "compliance": 1.0,
      "topo_eta_f": 0.0,
      "topo_computation_ms": 0.0
    },
    {
      "space": "scalar_grid",
      "budget": "high",
      "budget_frac": 0.3,
      "seed": 7,
      "n_refined": 19.0,
      "n_passed": 19.0,
      "n_rejected": 0.0,
      "reject_rate": 0.0,
      "psnr_gain": 6.988958262030103,
      "compliance": 1.0,
      "topo_eta_f": 0.0,
      "topo_computation_ms": 0.0
    },
    {
      "space": "scalar_grid",
      "budget": "high",
      "budget_frac": 0.3,
      "seed": 8,
      "n_refined": 19.0,
      "n_passed": 19.0,
      "n_rejected": 0.0,
      "reject_rate": 0.0,
      "psnr_gain": 5.450569451398227,
      "compliance": 1.0,
      "topo_eta_f": 0.0,
      "topo_computation_ms": 0.0
    },
    {
      "space": "scalar_grid",
      "budget": "high",
      "budget_frac": 0.3,
      "seed": 9,
      "n_refined": 19.0,
      "n_passed": 19.0,
      "n_rejected": 0.0,
      "reject_rate": 0.0,
      "psnr_gain": 5.934209240118996,
      "compliance": 1.0,
      "topo_eta_f": 0.0,
      "topo_computation_ms": 0.0
    },
    {
      "space": "scalar_grid",
      "budget": "high",
      "budget_frac": 0.3,
      "seed": 10,
      "n_refined": 19.0,
      "n_passed": 19.0,
      "n_rejected": 0.0,
      "reject_rate": 0.0,
      "psnr_gain": 6.076898261949175,
      "compliance": 1.0,
      "topo_eta_f": 0.0,
      "topo_computation_ms": 0.0
    },
    {
      "space": "scalar_grid",
      "budget": "high",
      "budget_frac": 0.3,
      "seed": 11,
      "n_refined": 19.0,
      "n_passed": 19.0,
      "n_rejected": 0.0,
      "reject_rate": 0.0,
      "psnr_gain": 9.724686489487887,
      "compliance": 1.0,
      "topo_eta_f": 0.0,
      "topo_computation_ms": 0.0
    },
    {
      "space": "scalar_grid",
      "budget": "high",
      "budget_frac": 0.3,
      "seed": 12,
      "n_refined": 19.0,
      "n_passed": 19.0,
      "n_rejected": 0.0,
      "reject_rate": 0.0,
      "psnr_gain": 8.301939523849228,
      "compliance": 1.0,
      "topo_eta_f": 0.0,
      "topo_computation_ms": 0.0
    },
    {
      "space": "scalar_grid",
      "budget": "high",
      "budget_frac": 0.3,
      "seed": 13,
      "n_refined": 19.0,
      "n_passed": 19.0,
      "n_rejected": 0.0,
      "reject_rate": 0.0,
      "psnr_gain": 6.766120043005007,
      "compliance": 1.0,
      "topo_eta_f": 0.0,
      "topo_computation_ms": 0.0
    },
    {
      "space": "scalar_grid",
      "budget": "high",
      "budget_frac": 0.3,
      "seed": 14,
      "n_refined": 19.0,
      "n_passed": 19.0,
      "n_rejected": 0.0,
      "reject_rate": 0.0,
      "psnr_gain": 7.533904883374817,
      "compliance": 1.0,
      "topo_eta_f": 0.0,
      "topo_computation_ms": 0.0
    },
    {
      "space": "scalar_grid",
      "budget": "high",
      "budget_frac": 0.3,
      "seed": 15,
      "n_refined": 19.0,
      "n_passed": 19.0,
      "n_rejected": 0.0,
      "reject_rate": 0.0,
      "psnr_gain": 8.052696840944432,
      "compliance": 1.0,
      "topo_eta_f": 0.0,
      "topo_computation_ms": 0.0
    },
    {
      "space": "scalar_grid",
      "budget": "high",
      "budget_frac": 0.3,
      "seed": 16,
      "n_refined": 19.0,
      "n_passed": 19.0,
      "n_rejected": 0.0,
      "reject_rate": 0.0,
      "psnr_gain": 6.857443935598614,
      "compliance": 1.0,
      "topo_eta_f": 0.0,
      "topo_computation_ms": 0.0
    },
    {
      "space": "scalar_grid",
      "budget": "high",
      "budget_frac": 0.3,
      "seed": 17,
      "n_refined": 19.0,
      "n_passed": 19.0,
      "n_rejected": 0.0,
      "reject_rate": 0.0,
      "psnr_gain": 9.509445271881798,
      "compliance": 1.0,
      "topo_eta_f": 0.0,
      "topo_computation_ms": 0.0
    },
    {
      "space": "scalar_grid",
      "budget": "high",
      "budget_frac": 0.3,
      "seed": 18,
      "n_refined": 19.0,
      "n_passed": 19.0,
      "n_rejected": 0.0,
      "reject_rate": 0.0,
      "psnr_gain": 8.028075672966324,
      "compliance": 1.0,
      "topo_eta_f": 0.0,
      "topo_computation_ms": 0.0
    },
    {
      "space": "scalar_grid",
      "budget": "high",
      "budget_frac": 0.3,
      "seed": 19,
      "n_refined": 19.0,
      "n_passed": 19.0,
      "n_rejected": 0.0,
      "reject_rate": 0.0,
      "psnr_gain": 7.291692396682251,
      "compliance": 1.0,
      "topo_eta_f": 0.0,
      "topo_computation_ms": 0.0
    },
    {
      "space": "vector_grid",
      "budget": "low",
      "budget_frac": 0.1,
      "seed": 0,
      "n_refined": 1.0,
      "n_passed": 1.0,
      "n_rejected": 0.0,
      "reject_rate": 0.0,
      "psnr_gain": 0.3120616918881076,
      "compliance": 1.0,
      "topo_eta_f": 0.0,
      "topo_computation_ms": 0.0
    },
    {
      "space": "vector_grid",
      "budget": "low",
      "budget_frac": 0.1,
      "seed": 1,
      "n_refined": 1.0,
      "n_passed": 1.0,
      "n_rejected": 0.0,
      "reject_rate": 0.0,
      "psnr_gain": 0.39184417266468685,
      "compliance": 1.0,
      "topo_eta_f": 0.0,
      "topo_computation_ms": 0.0
    },
    {
      "space": "vector_grid",
      "budget": "low",
      "budget_frac": 0.1,
      "seed": 2,
      "n_refined": 1.0,
      "n_passed": 1.0,
      "n_rejected": 0.0,
      "reject_rate": 0.0,
      "psnr_gain": 0.4081151614746936,
      "compliance": 1.0,
      "topo_eta_f": 0.0,
      "topo_computation_ms": 0.0
    },
    {
      "space": "vector_grid",
      "budget": "low",
      "budget_frac": 0.1,
      "seed": 3,
      "n_refined": 1.0,
      "n_passed": 1.0,
      "n_rejected": 0.0,
      "reject_rate": 0.0,
      "psnr_gain": 0.3081946600474339,
      "compliance": 1.0,
      "topo_eta_f": 0.0,
      "topo_computation_ms": 0.0
    },
    {
      "space": "vector_grid",
      "budget": "low",
      "budget_frac": 0.1,
      "seed": 4,
      "n_refined": 1.0,
      "n_passed": 1.0,
      "n_rejected": 0.0,
      "reject_rate": 0.0,
      "psnr_gain": 0.38671760903710606,
      "compliance": 1.0,
      "topo_eta_f": 0.0,
      "topo_computation_ms": 0.0
    },
    {
      "space": "vector_grid",
      "budget": "low",
      "budget_frac": 0.1,
      "seed": 5,
      "n_refined": 1.0,
      "n_passed": 1.0,
      "n_rejected": 0.0,
      "reject_rate": 0.0,
      "psnr_gain": 0.41535362066757386,
      "compliance": 1.0,
      "topo_eta_f": 0.0,
      "topo_computation_ms": 0.0
    },
    {
      "space": "vector_grid",
      "budget": "low",
      "budget_frac": 0.1,
      "seed": 6,
      "n_refined": 1.0,
      "n_passed": 1.0,
      "n_rejected": 0.0,
      "reject_rate": 0.0,
      "psnr_gain": 0.337260584378722,
      "compliance": 1.0,
      "topo_eta_f": 0.0,
      "topo_computation_ms": 0.0
    },
    {
      "space": "vector_grid",
      "budget": "low",
      "budget_frac": 0.1,
      "seed": 7,
      "n_refined": 1.0,
      "n_passed": 1.0,
      "n_rejected": 0.0,
      "reject_rate": 0.0,
      "psnr_gain": 0.30923408241555705,
      "compliance": 1.0,
      "topo_eta_f": 0.0,
      "topo_computation_ms": 0.0
    },
    {
      "space": "vector_grid",
      "budget": "low",
      "budget_frac": 0.1,
      "seed": 8,
      "n_refined": 1.0,
      "n_passed": 1.0,
      "n_rejected": 0.0,
      "reject_rate": 0.0,
      "psnr_gain": 0.5379441826531561,
      "compliance": 1.0,
      "topo_eta_f": 0.0,
      "topo_computation_ms": 0.0
    },
    {
      "space": "vector_grid",
      "budget": "low",
      "budget_frac": 0.1,
      "seed": 9,
      "n_refined": 1.0,
      "n_passed": 1.0,
      "n_rejected": 0.0,
      "reject_rate": 0.0,
      "psnr_gain": 0.40355699045747073,
      "compliance": 1.0,
      "topo_eta_f": 0.0,
      "topo_computation_ms": 0.0
    },
    {
      "space": "vector_grid",
      "budget": "low",
      "budget_frac": 0.1,
      "seed": 10,
      "n_refined": 1.0,
      "n_passed": 1.0,
      "n_rejected": 0.0,
      "reject_rate": 0.0,
      "psnr_gain": 0.3068710678815272,
      "compliance": 1.0,
      "topo_eta_f": 0.0,
      "topo_computation_ms": 0.0
    },
    {
      "space": "vector_grid",
      "budget": "low",
      "budget_frac": 0.1,
      "seed": 11,
      "n_refined": 1.0,
      "n_passed": 1.0,
      "n_rejected": 0.0,
      "reject_rate": 0.0,
      "psnr_gain": 0.39796058133532597,
      "compliance": 1.0,
      "topo_eta_f": 0.0,
      "topo_computation_ms": 0.0
    },
    {
      "space": "vector_grid",
      "budget": "low",
      "budget_frac": 0.1,
      "seed": 12,
      "n_refined": 1.0,
      "n_passed": 1.0,
      "n_rejected": 0.0,
      "reject_rate": 0.0,
      "psnr_gain": 0.5493148757239936,
      "compliance": 1.0,
      "topo_eta_f": 0.0,
      "topo_computation_ms": 0.0
    },
    {
      "space": "vector_grid",
      "budget": "low",
      "budget_frac": 0.1,
      "seed": 13,
      "n_refined": 1.0,
      "n_passed": 1.0,
      "n_rejected": 0.0,
      "reject_rate": 0.0,
      "psnr_gain": 0.41120990988037676,
      "compliance": 1.0,
      "topo_eta_f": 0.0,
      "topo_computation_ms": 0.0
    },
    {
      "space": "vector_grid",
      "budget": "low",
      "budget_frac": 0.1,
      "seed": 14,
      "n_refined": 1.0,
      "n_passed": 1.0,
      "n_rejected": 0.0,
      "reject_rate": 0.0,
      "psnr_gain": 0.38433771078589274,
      "compliance": 1.0,
      "topo_eta_f": 0.0,
      "topo_computation_ms": 0.0
    },
    {
      "space": "vector_grid",
      "budget": "low",
      "budget_frac": 0.1,
      "seed": 15,
      "n_refined": 1.0,
      "n_passed": 1.0,
      "n_rejected": 0.0,
      "reject_rate": 0.0,
      "psnr_gain": 0.4101241534509015,
      "compliance": 1.0,
      "topo_eta_f": 0.0,
      "topo_computation_ms": 0.0
    },
    {
      "space": "vector_grid",
      "budget": "low",
      "budget_frac": 0.1,
      "seed": 16,
      "n_refined": 1.0,
      "n_passed": 1.0,
      "n_rejected": 0.0,
      "reject_rate": 0.0,
      "psnr_gain": 0.3868752134050695,
      "compliance": 1.0,
      "topo_eta_f": 0.0,
      "topo_computation_ms": 0.0
    },
    {
      "space": "vector_grid",
      "budget": "low",
      "budget_frac": 0.1,
      "seed": 17,
      "n_refined": 1.0,
      "n_passed": 1.0,
      "n_rejected": 0.0,
      "reject_rate": 0.0,
      "psnr_gain": 0.43076471966544005,
      "compliance": 1.0,
      "topo_eta_f": 0.0,
      "topo_computation_ms": 0.0
    },
    {
      "space": "vector_grid",
      "budget": "low",
      "budget_frac": 0.1,
      "seed": 18,
      "n_refined": 1.0,
      "n_passed": 1.0,
      "n_rejected": 0.0,
      "reject_rate": 0.0,
      "psnr_gain": 0.3101202099150093,
      "compliance": 1.0,
      "topo_eta_f": 0.0,
      "topo_computation_ms": 0.0
    },
    {
      "space": "vector_grid",
      "budget": "low",
      "budget_frac": 0.1,
      "seed": 19,
      "n_refined": 1.0,
      "n_passed": 1.0,
      "n_rejected": 0.0,
      "reject_rate": 0.0,
      "psnr_gain": 0.3065222645510417,
      "compliance": 1.0,
      "topo_eta_f": 0.0,
      "topo_computation_ms": 0.0
    },
    {
      "space": "vector_grid",
      "budget": "high",
      "budget_frac": 0.3,
      "seed": 0,
      "n_refined": 4.0,
      "n_passed": 4.0,
      "n_rejected": 0.0,
      "reject_rate": 0.0,
      "psnr_gain": 1.4377478827647394,
      "compliance": 1.0,
      "topo_eta_f": 0.0,
      "topo_computation_ms": 0.0
    },
    {
      "space": "vector_grid",
      "budget": "high",
      "budget_frac": 0.3,
      "seed": 1,
      "n_refined": 4.0,
      "n_passed": 4.0,
      "n_rejected": 0.0,
      "reject_rate": 0.0,
      "psnr_gain": 1.6561272491631236,
      "compliance": 1.0,
      "topo_eta_f": 0.0,
      "topo_computation_ms": 0.0
    },
    {
      "space": "vector_grid",
      "budget": "high",
      "budget_frac": 0.3,
      "seed": 2,
      "n_refined": 4.0,
      "n_passed": 4.0,
      "n_rejected": 0.0,
      "reject_rate": 0.0,
      "psnr_gain": 1.3810486737579026,
      "compliance": 1.0,
      "topo_eta_f": 0.0,
      "topo_computation_ms": 0.0
    },
    {
      "space": "vector_grid",
      "budget": "high",
      "budget_frac": 0.3,
      "seed": 3,
      "n_refined": 4.0,
      "n_passed": 4.0,
      "n_rejected": 0.0,
      "reject_rate": 0.0,
      "psnr_gain": 1.4091970814512962,
      "compliance": 1.0,
      "topo_eta_f": 0.0,
      "topo_computation_ms": 0.0
    },
    {
      "space": "vector_grid",
      "budget": "high",
      "budget_frac": 0.3,
      "seed": 4,
      "n_refined": 4.0,
      "n_passed": 4.0,
      "n_rejected": 0.0,
      "reject_rate": 0.0,
      "psnr_gain": 1.4887965742496085,
      "compliance": 1.0,
      "topo_eta_f": 0.0,
      "topo_computation_ms": 0.0
    },
    {
      "space": "vector_grid",
      "budget": "high",
      "budget_frac": 0.3,
      "seed": 5,
      "n_refined": 4.0,
      "n_passed": 4.0,
      "n_rejected": 0.0,
      "reject_rate": 0.0,
      "psnr_gain": 1.5472475894935904,
      "compliance": 1.0,
      "topo_eta_f": 0.0,
      "topo_computation_ms": 0.0
    },
    {
      "space": "vector_grid",
      "budget": "high",
      "budget_frac": 0.3,
      "seed": 6,
      "n_refined": 4.0,
      "n_passed": 4.0,
      "n_rejected": 0.0,
      "reject_rate": 0.0,
      "psnr_gain": 1.376906353716528,
      "compliance": 1.0,
      "topo_eta_f": 0.0,
      "topo_computation_ms": 0.0
    },
    {
      "space": "vector_grid",
      "budget": "high",
      "budget_frac": 0.3,
      "seed": 7,
      "n_refined": 4.0,
      "n_passed": 4.0,
      "n_rejected": 0.0,
      "reject_rate": 0.0,
      "psnr_gain": 1.357564429735998,
      "compliance": 1.0,
      "topo_eta_f": 0.0,
      "topo_computation_ms": 0.0
    },
    {
      "space": "vector_grid",
      "budget": "high",
      "budget_frac": 0.3,
      "seed": 8,
      "n_refined": 4.0,
      "n_passed": 4.0,
      "n_rejected": 0.0,
      "reject_rate": 0.0,
      "psnr_gain": 1.5487154877406546,
      "compliance": 1.0,
      "topo_eta_f": 0.0,
      "topo_computation_ms": 0.0
    },
    {
      "space": "vector_grid",
      "budget": "high",
      "budget_frac": 0.3,
      "seed": 9,
      "n_refined": 4.0,
      "n_passed": 4.0,
      "n_rejected": 0.0,
      "reject_rate": 0.0,
      "psnr_gain": 1.3775841058828995,
      "compliance": 1.0,
      "topo_eta_f": 0.0,
      "topo_computation_ms": 0.0
    },
    {
      "space": "vector_grid",
      "budget": "high",
      "budget_frac": 0.3,
      "seed": 10,
      "n_refined": 4.0,
      "n_passed": 4.0,
      "n_rejected": 0.0,
      "reject_rate": 0.0,
      "psnr_gain": 1.399112155841081,
      "compliance": 1.0,
      "topo_eta_f": 0.0,
      "topo_computation_ms": 0.0
    },
    {
      "space": "vector_grid",
      "budget": "high",
      "budget_frac": 0.3,
      "seed": 11,
      "n_refined": 4.0,
      "n_passed": 4.0,
      "n_rejected": 0.0,
      "reject_rate": 0.0,
      "psnr_gain": 1.6682924426921488,
      "compliance": 1.0,
      "topo_eta_f": 0.0,
      "topo_computation_ms": 0.0
    },
    {
      "space": "vector_grid",
      "budget": "high",
      "budget_frac": 0.3,
      "seed": 12,
      "n_refined": 4.0,
      "n_passed": 4.0,
      "n_rejected": 0.0,
      "reject_rate": 0.0,
      "psnr_gain": 1.6126442342588092,
      "compliance": 1.0,
      "topo_eta_f": 0.0,
      "topo_computation_ms": 0.0
    },
    {
      "space": "vector_grid",
      "budget": "high",
      "budget_frac": 0.3,
      "seed": 13,
      "n_refined": 4.0,
      "n_passed": 4.0,
      "n_rejected": 0.0,
      "reject_rate": 0.0,
      "psnr_gain": 1.3125454284200941,
      "compliance": 1.0,
      "topo_eta_f": 0.0,
      "topo_computation_ms": 0.0
    },
    {
      "space": "vector_grid",
      "budget": "high",
      "budget_frac": 0.3,
      "seed": 14,
      "n_refined": 4.0,
      "n_passed": 4.0,
      "n_rejected": 0.0,
      "reject_rate": 0.0,
      "psnr_gain": 1.8423333326101101,
      "compliance": 1.0,
      "topo_eta_f": 0.0,
      "topo_computation_ms": 0.0
    },
    {
      "space": "vector_grid",
      "budget": "high",
      "budget_frac": 0.3,
      "seed": 15,
      "n_refined": 4.0,
      "n_passed": 4.0,
      "n_rejected": 0.0,
      "reject_rate": 0.0,
      "psnr_gain": 1.3889383788646192,
      "compliance": 1.0,
      "topo_eta_f": 0.0,
      "topo_computation_ms": 0.0
    },
    {
      "space": "vector_grid",
      "budget": "high",
      "budget_frac": 0.3,
      "seed": 16,
      "n_refined": 4.0,
      "n_passed": 4.0,
      "n_rejected": 0.0,
      "reject_rate": 0.0,
      "psnr_gain": 1.624075564291779,
      "compliance": 1.0,
      "topo_eta_f": 0.0,
      "topo_computation_ms": 0.0
    },
    {
      "space": "vector_grid",
      "budget": "high",
      "budget_frac": 0.3,
      "seed": 17,
      "n_refined": 4.0,
      "n_passed": 4.0,
      "n_rejected": 0.0,
      "reject_rate": 0.0,
      "psnr_gain": 1.551543667183541,
      "compliance": 1.0,
      "topo_eta_f": 0.0,
      "topo_computation_ms": 0.0
    },
    {
      "space": "vector_grid",
      "budget": "high",
      "budget_frac": 0.3,
      "seed": 18,
      "n_refined": 4.0,
      "n_passed": 4.0,
      "n_rejected": 0.0,
      "reject_rate": 0.0,
      "psnr_gain": 1.3168014592498132,
      "compliance": 1.0,
      "topo_eta_f": 0.0,
      "topo_computation_ms": 0.0
    },
    {
      "space": "vector_grid",
      "budget": "high",
      "budget_frac": 0.3,
      "seed": 19,
      "n_refined": 4.0,
      "n_passed": 4.0,
      "n_rejected": 0.0,
      "reject_rate": 0.0,
      "psnr_gain": 1.5057443978438414,
      "compliance": 1.0,
      "topo_eta_f": 0.0,
      "topo_computation_ms": 0.0
    },
    {
      "space": "irregular_graph",
      "budget": "low",
      "budget_frac": 0.1,
      "seed": 0,
      "n_refined": 1.0,
      "n_passed": 1.0,
      "n_rejected": 0.0,
      "reject_rate": 0.0,
      "psnr_gain": 1.7245267348050248,
      "compliance": 1.0,
      "topo_eta_f": 1.0658150535513318,
      "topo_computation_ms": 59.0803999803029
    },
    {
      "space": "irregular_graph",
      "budget": "low",
      "budget_frac": 0.1,
      "seed": 1,
      "n_refined": 1.0,
      "n_passed": 1.0,
      "n_rejected": 0.0,
      "reject_rate": 0.0,
      "psnr_gain": 1.0594512232097486,
      "compliance": 1.0,
      "topo_eta_f": 1.0734330336734779,
      "topo_computation_ms": 55.24200003128499
    },
    {
      "space": "irregular_graph",
      "budget": "low",
      "budget_frac": 0.1,
      "seed": 2,
      "n_refined": 1.0,
      "n_passed": 0.0,
      "n_rejected": 0.0,
      "reject_rate": 0.0,
      "psnr_gain": 0.6656536362063719,
      "compliance": 1.0,
      "topo_eta_f": 1.0455175091434783,
      "topo_computation_ms": 52.03530000289902
    },
    {
      "space": "irregular_graph",
      "budget": "low",
      "budget_frac": 0.1,
      "seed": 3,
      "n_refined": 1.0,
      "n_passed": 1.0,
      "n_rejected": 0.0,
      "reject_rate": 0.0,
      "psnr_gain": 1.451274477243416,
      "compliance": 1.0,
      "topo_eta_f": 1.0176088113075705,
      "topo_computation_ms": 55.0224999897182
    },
    {
      "space": "irregular_graph",
      "budget": "low",
      "budget_frac": 0.1,
      "seed": 4,
      "n_refined": 1.0,
      "n_passed": 1.0,
      "n_rejected": 0.0,
      "reject_rate": 0.0,
      "psnr_gain": 1.0187861885143157,
      "compliance": 1.0,
      "topo_eta_f": 1.0426928961313042,
      "topo_computation_ms": 55.67580001661554
    },
    {
      "space": "irregular_graph",
      "budget": "low",
      "budget_frac": 0.1,
      "seed": 5,
      "n_refined": 1.0,
      "n_passed": 1.0,
      "n_rejected": 0.0,
      "reject_rate": 0.0,
      "psnr_gain": 1.5394912910211414,
      "compliance": 1.0,
      "topo_eta_f": 1.0960578047576972,
      "topo_computation_ms": 52.16839996865019
    },
    {
      "space": "irregular_graph",
      "budget": "low",
      "budget_frac": 0.1,
      "seed": 6,
      "n_refined": 1.0,
      "n_passed": 1.0,
      "n_rejected": 0.0,
      "reject_rate": 0.0,
      "psnr_gain": 1.6189814543735164,
      "compliance": 1.0,
      "topo_eta_f": 1.0299006730602671,
      "topo_computation_ms": 54.713199962861836
    },
    {
      "space": "irregular_graph",
      "budget": "low",
      "budget_frac": 0.1,
      "seed": 7,
      "n_refined": 1.0,
      "n_passed": 1.0,
      "n_rejected": 0.0,
      "reject_rate": 0.0,
      "psnr_gain": 1.324985438691634,
      "compliance": 1.0,
      "topo_eta_f": 1.0014040106717388,
      "topo_computation_ms": 53.80400002468377
    },
    {
      "space": "irregular_graph",
      "budget": "low",
      "budget_frac": 0.1,
      "seed": 8,
      "n_refined": 1.0,
      "n_passed": 1.0,
      "n_rejected": 0.0,
      "reject_rate": 0.0,
      "psnr_gain": 1.858541934058561,
      "compliance": 1.0,
      "topo_eta_f": 1.0168692777007344,
      "topo_computation_ms": 60.903299949131906
    },
    {
      "space": "irregular_graph",
      "budget": "low",
      "budget_frac": 0.1,
      "seed": 9,
      "n_refined": 1.0,
      "n_passed": 1.0,
      "n_rejected": 0.0,
      "reject_rate": 0.0,
      "psnr_gain": 2.153457493528517,
      "compliance": 1.0,
      "topo_eta_f": 1.0704357807317515,
      "topo_computation_ms": 62.453499995172024
    },
    {
      "space": "irregular_graph",
      "budget": "low",
      "budget_frac": 0.1,
      "seed": 10,
      "n_refined": 1.0,
      "n_passed": 1.0,
      "n_rejected": 0.0,
      "reject_rate": 0.0,
      "psnr_gain": 1.2301855813007023,
      "compliance": 1.0,
      "topo_eta_f": 1.0065422459544842,
      "topo_computation_ms": 64.01550001464784
    },
    {
      "space": "irregular_graph",
      "budget": "low",
      "budget_frac": 0.1,
      "seed": 11,
      "n_refined": 1.0,
      "n_passed": 1.0,
      "n_rejected": 0.0,
      "reject_rate": 0.0,
      "psnr_gain": 2.4005034317153253,
      "compliance": 1.0,
      "topo_eta_f": 1.0401640454109524,
      "topo_computation_ms": 57.912299991585314
    },
    {
      "space": "irregular_graph",
      "budget": "low",
      "budget_frac": 0.1,
      "seed": 12,
      "n_refined": 1.0,
      "n_passed": 1.0,
      "n_rejected": 0.0,
      "reject_rate": 0.0,
      "psnr_gain": 1.8893176816888104,
      "compliance": 1.0,
      "topo_eta_f": 1.0943903205338312,
      "topo_computation_ms": 52.02090000966564
    },
    {
      "space": "irregular_graph",
      "budget": "low",
      "budget_frac": 0.1,
      "seed": 13,
      "n_refined": 1.0,
      "n_passed": 1.0,
      "n_rejected": 0.0,
      "reject_rate": 0.0,
      "psnr_gain": 1.6707376968532959,
      "compliance": 1.0,
      "topo_eta_f": 1.0853026716649397,
      "topo_computation_ms": 52.65010002767667
    },
    {
      "space": "irregular_graph",
      "budget": "low",
      "budget_frac": 0.1,
      "seed": 14,
      "n_refined": 1.0,
      "n_passed": 1.0,
      "n_rejected": 0.0,
      "reject_rate": 0.0,
      "psnr_gain": 1.4928555466824598,
      "compliance": 1.0,
      "topo_eta_f": 1.0917390630564026,
      "topo_computation_ms": 52.84919997211546
    },
    {
      "space": "irregular_graph",
      "budget": "low",
      "budget_frac": 0.1,
      "seed": 15,
      "n_refined": 1.0,
      "n_passed": 1.0,
      "n_rejected": 0.0,
      "reject_rate": 0.0,
      "psnr_gain": 0.788981933557551,
      "compliance": 1.0,
      "topo_eta_f": 1.0377318141279184,
      "topo_computation_ms": 63.37740004528314
    },
    {
      "space": "irregular_graph",
      "budget": "low",
      "budget_frac": 0.1,
      "seed": 16,
      "n_refined": 1.0,
      "n_passed": 1.0,
      "n_rejected": 0.0,
      "reject_rate": 0.0,
      "psnr_gain": 0.7379751971951869,
      "compliance": 1.0,
      "topo_eta_f": 1.0995194396064922,
      "topo_computation_ms": 63.70630004676059
    },
    {
      "space": "irregular_graph",
      "budget": "low",
      "budget_frac": 0.1,
      "seed": 17,
      "n_refined": 1.0,
      "n_passed": 1.0,
      "n_rejected": 0.0,
      "reject_rate": 0.0,
      "psnr_gain": 0.9057405563388237,
      "compliance": 1.0,
      "topo_eta_f": 1.075765635517578,
      "topo_computation_ms": 53.326499997638166
    },
    {
      "space": "irregular_graph",
      "budget": "low",
      "budget_frac": 0.1,
      "seed": 18,
      "n_refined": 1.0,
      "n_passed": 1.0,
      "n_rejected": 0.0,
      "reject_rate": 0.0,
      "psnr_gain": 0.7550790707962811,
      "compliance": 1.0,
      "topo_eta_f": 1.0364784565059535,
      "topo_computation_ms": 57.57539998739958
    },
    {
      "space": "irregular_graph",
      "budget": "low",
      "budget_frac": 0.1,
      "seed": 19,
      "n_refined": 1.0,
      "n_passed": 1.0,
      "n_rejected": 0.0,
      "reject_rate": 0.0,
      "psnr_gain": 0.7582130410423034,
      "compliance": 1.0,
      "topo_eta_f": 1.0860512584967734,
      "topo_computation_ms": 54.66399999568239
    },
    {
      "space": "irregular_graph",
      "budget": "high",
      "budget_frac": 0.3,
      "seed": 0,
      "n_refined": 3.0,
      "n_passed": 3.0,
      "n_rejected": 0.0,
      "reject_rate": 0.0,
      "psnr_gain": 3.0523799702620806,
      "compliance": 1.0,
      "topo_eta_f": 1.0658150535513318,
      "topo_computation_ms": 56.152100034523755
    },
    {
      "space": "irregular_graph",
      "budget": "high",
      "budget_frac": 0.3,
      "seed": 1,
      "n_refined": 3.0,
      "n_passed": 3.0,
      "n_rejected": 0.0,
      "reject_rate": 0.0,
      "psnr_gain": 3.241864808528451,
      "compliance": 1.0,
      "topo_eta_f": 1.0734330336734779,
      "topo_computation_ms": 53.78539999946952
    },
    {
      "space": "irregular_graph",
      "budget": "high",
      "budget_frac": 0.3,
      "seed": 2,
      "n_refined": 3.0,
      "n_passed": 1.0,
      "n_rejected": 0.0,
      "reject_rate": 0.0,
      "psnr_gain": 2.0215563701387644,
      "compliance": 1.0,
      "topo_eta_f": 1.0455175091434783,
      "topo_computation_ms": 61.53140001697466
    },
    {
      "space": "irregular_graph",
      "budget": "high",
      "budget_frac": 0.3,
      "seed": 3,
      "n_refined": 3.0,
      "n_passed": 3.0,
      "n_rejected": 0.0,
      "reject_rate": 0.0,
      "psnr_gain": 3.4682163342594876,
      "compliance": 1.0,
      "topo_eta_f": 1.0176088113075705,
      "topo_computation_ms": 56.623100012075156
    },
    {
      "space": "irregular_graph",
      "budget": "high",
      "budget_frac": 0.3,
      "seed": 4,
      "n_refined": 3.0,
      "n_passed": 3.0,
      "n_rejected": 0.0,
      "reject_rate": 0.0,
      "psnr_gain": 2.9004638428392333,
      "compliance": 1.0,
      "topo_eta_f": 1.0426928961313042,
      "topo_computation_ms": 63.945100002456456
    },
    {
      "space": "irregular_graph",
      "budget": "high",
      "budget_frac": 0.3,
      "seed": 5,
      "n_refined": 3.0,
      "n_passed": 3.0,
      "n_rejected": 0.0,
      "reject_rate": 0.0,
      "psnr_gain": 3.605907685269406,
      "compliance": 1.0,
      "topo_eta_f": 1.0960578047576972,
      "topo_computation_ms": 53.65080002229661
    },
    {
      "space": "irregular_graph",
      "budget": "high",
      "budget_frac": 0.3,
      "seed": 6,
      "n_refined": 3.0,
      "n_passed": 3.0,
      "n_rejected": 0.0,
      "reject_rate": 0.0,
      "psnr_gain": 3.087424258234714,
      "compliance": 1.0,
      "topo_eta_f": 1.0299006730602671,
      "topo_computation_ms": 58.167599956505
    },
    {
      "space": "irregular_graph",
      "budget": "high",
      "budget_frac": 0.3,
      "seed": 7,
      "n_refined": 3.0,
      "n_passed": 2.0,
      "n_rejected": 0.0,
      "reject_rate": 0.0,
      "psnr_gain": 3.8458997762851332,
      "compliance": 1.0,
      "topo_eta_f": 1.0014040106717388,
      "topo_computation_ms": 58.21270000888035
    },
    {
      "space": "irregular_graph",
      "budget": "high",
      "budget_frac": 0.3,
      "seed": 8,
      "n_refined": 3.0,
      "n_passed": 2.0,
      "n_rejected": 0.0,
      "reject_rate": 0.0,
      "psnr_gain": 4.4416191100377205,
      "compliance": 1.0,
      "topo_eta_f": 1.0168692777007344,
      "topo_computation_ms": 54.31709997355938
    },
    {
      "space": "irregular_graph",
      "budget": "high",
      "budget_frac": 0.3,
      "seed": 9,
      "n_refined": 3.0,
      "n_passed": 3.0,
      "n_rejected": 0.0,
      "reject_rate": 0.0,
      "psnr_gain": 4.4372953240224255,
      "compliance": 1.0,
      "topo_eta_f": 1.0704357807317515,
      "topo_computation_ms": 57.096000004094094
    },
    {
      "space": "irregular_graph",
      "budget": "high",
      "budget_frac": 0.3,
      "seed": 10,
      "n_refined": 3.0,
      "n_passed": 3.0,
      "n_rejected": 0.0,
      "reject_rate": 0.0,
      "psnr_gain": 3.8267901011565506,
      "compliance": 1.0,
      "topo_eta_f": 1.0065422459544842,
      "topo_computation_ms": 54.63440000312403
    },
    {
      "space": "irregular_graph",
      "budget": "high",
      "budget_frac": 0.3,
      "seed": 11,
      "n_refined": 3.0,
      "n_passed": 3.0,
      "n_rejected": 0.0,
      "reject_rate": 0.0,
      "psnr_gain": 4.565411922093258,
      "compliance": 1.0,
      "topo_eta_f": 1.0401640454109524,
      "topo_computation_ms": 52.360699977725744
    },
    {
      "space": "irregular_graph",
      "budget": "high",
      "budget_frac": 0.3,
      "seed": 12,
      "n_refined": 3.0,
      "n_passed": 3.0,
      "n_rejected": 0.0,
      "reject_rate": 0.0,
      "psnr_gain": 4.470432020789813,
      "compliance": 1.0,
      "topo_eta_f": 1.0943903205338312,
      "topo_computation_ms": 59.34400000842288
    },
    {
      "space": "irregular_graph",
      "budget": "high",
      "budget_frac": 0.3,
      "seed": 13,
      "n_refined": 3.0,
      "n_passed": 3.0,
      "n_rejected": 0.0,
      "reject_rate": 0.0,
      "psnr_gain": 4.222134561337169,
      "compliance": 1.0,
      "topo_eta_f": 1.0853026716649397,
      "topo_computation_ms": 54.91589999292046
    },
    {
      "space": "irregular_graph",
      "budget": "high",
      "budget_frac": 0.3,
      "seed": 14,
      "n_refined": 3.0,
      "n_passed": 3.0,
      "n_rejected": 0.0,
      "reject_rate": 0.0,
      "psnr_gain": 3.7323627810808055,
      "compliance": 1.0,
      "topo_eta_f": 1.0917390630564026,
      "topo_computation_ms": 55.969799985177815
    },
    {
      "space": "irregular_graph",
      "budget": "high",
      "budget_frac": 0.3,
      "seed": 15,
      "n_refined": 3.0,
      "n_passed": 3.0,
      "n_rejected": 0.0,
      "reject_rate": 0.0,
      "psnr_gain": 2.2192669312952766,
      "compliance": 1.0,
      "topo_eta_f": 1.0377318141279184,
      "topo_computation_ms": 55.88060000445694
    },
    {
      "space": "irregular_graph",
      "budget": "high",
      "budget_frac": 0.3,
      "seed": 16,
      "n_refined": 4.0,
      "n_passed": 4.0,
      "n_rejected": 0.0,
      "reject_rate": 0.0,
      "psnr_gain": 2.648182985253733,
      "compliance": 1.0,
      "topo_eta_f": 1.0995194396064922,
      "topo_computation_ms": 54.720700019970536
    },
    {
      "space": "irregular_graph",
      "budget": "high",
      "budget_frac": 0.3,
      "seed": 17,
      "n_refined": 3.0,
      "n_passed": 3.0,
      "n_rejected": 0.0,
      "reject_rate": 0.0,
      "psnr_gain": 2.5941984468622756,
      "compliance": 1.0,
      "topo_eta_f": 1.075765635517578,
      "topo_computation_ms": 53.78680001012981
    },
    {
      "space": "irregular_graph",
      "budget": "high",
      "budget_frac": 0.3,
      "seed": 18,
      "n_refined": 4.0,
      "n_passed": 4.0,
      "n_rejected": 0.0,
      "reject_rate": 0.0,
      "psnr_gain": 4.384495934127614,
      "compliance": 1.0,
      "topo_eta_f": 1.0364784565059535,
      "topo_computation_ms": 56.65669997688383
    },
    {
      "space": "irregular_graph",
      "budget": "high",
      "budget_frac": 0.3,
      "seed": 19,
      "n_refined": 3.0,
      "n_passed": 3.0,
      "n_rejected": 0.0,
      "reject_rate": 0.0,
      "psnr_gain": 2.6205962474654285,
      "compliance": 1.0,
      "topo_eta_f": 1.0860512584967734,
      "topo_computation_ms": 54.420100001152605
    },
    {
      "space": "tree_hierarchy",
      "budget": "low",
      "budget_frac": 0.1,
      "seed": 0,
      "n_refined": 1.0,
      "n_passed": 1.0,
      "n_rejected": 0.0,
      "reject_rate": 0.0,
      "psnr_gain": 1.0029523850848037,
      "compliance": 1.0,
      "topo_eta_f": 0.0,
      "topo_computation_ms": 0.0
    },
    {
      "space": "tree_hierarchy",
      "budget": "low",
      "budget_frac": 0.1,
      "seed": 1,
      "n_refined": 1.0,
      "n_passed": 1.0,
      "n_rejected": 0.0,
      "reject_rate": 0.0,
      "psnr_gain": 1.2122826821848438,
      "compliance": 1.0,
      "topo_eta_f": 0.0,
      "topo_computation_ms": 0.0
    },
    {
      "space": "tree_hierarchy",
      "budget": "low",
      "budget_frac": 0.1,
      "seed": 2,
      "n_refined": 1.0,
      "n_passed": 0.0,
      "n_rejected": 0.0,
      "reject_rate": 0.0,
      "psnr_gain": 0.8420822347739332,
      "compliance": 1.0,
      "topo_eta_f": 0.0,
      "topo_computation_ms": 0.0
    },
    {
      "space": "tree_hierarchy",
      "budget": "low",
      "budget_frac": 0.1,
      "seed": 3,
      "n_refined": 1.0,
      "n_passed": 1.0,
      "n_rejected": 0.0,
      "reject_rate": 0.0,
      "psnr_gain": 1.161387093349445,
      "compliance": 1.0,
      "topo_eta_f": 0.0,
      "topo_computation_ms": 0.0
    },
    {
      "space": "tree_hierarchy",
      "budget": "low",
      "budget_frac": 0.1,
      "seed": 4,
      "n_refined": 1.0,
      "n_passed": 1.0,
      "n_rejected": 0.0,
      "reject_rate": 0.0,
      "psnr_gain": 1.228701056837462,
      "compliance": 1.0,
      "topo_eta_f": 0.0,
      "topo_computation_ms": 0.0
    },
    {
      "space": "tree_hierarchy",
      "budget": "low",
      "budget_frac": 0.1,
      "seed": 5,
      "n_refined": 1.0,
      "n_passed": 1.0,
      "n_rejected": 0.0,
      "reject_rate": 0.0,
      "psnr_gain": 0.9694707236190432,
      "compliance": 1.0,
      "topo_eta_f": 0.0,
      "topo_computation_ms": 0.0
    },
    {
      "space": "tree_hierarchy",
      "budget": "low",
      "budget_frac": 0.1,
      "seed": 6,
      "n_refined": 1.0,
      "n_passed": 1.0,
      "n_rejected": 0.0,
      "reject_rate": 0.0,
      "psnr_gain": 1.1789551858478795,
      "compliance": 1.0,
      "topo_eta_f": 0.0,
      "topo_computation_ms": 0.0
    },
    {
      "space": "tree_hierarchy",
      "budget": "low",
      "budget_frac": 0.1,
      "seed": 7,
      "n_refined": 1.0,
      "n_passed": 1.0,
      "n_rejected": 0.0,
      "reject_rate": 0.0,
      "psnr_gain": 1.1073368441062161,
      "compliance": 1.0,
      "topo_eta_f": 0.0,
      "topo_computation_ms": 0.0
    },
    {
      "space": "tree_hierarchy",
      "budget": "low",
      "budget_frac": 0.1,
      "seed": 8,
      "n_refined": 1.0,
      "n_passed": 1.0,
      "n_rejected": 0.0,
      "reject_rate": 0.0,
      "psnr_gain": 0.9483127095973582,
      "compliance": 1.0,
      "topo_eta_f": 0.0,
      "topo_computation_ms": 0.0
    },
    {
      "space": "tree_hierarchy",
      "budget": "low",
      "budget_frac": 0.1,
      "seed": 9,
      "n_refined": 1.0,
      "n_passed": 1.0,
      "n_rejected": 0.0,
      "reject_rate": 0.0,
      "psnr_gain": 1.3379243161922059,
      "compliance": 1.0,
      "topo_eta_f": 0.0,
      "topo_computation_ms": 0.0
    },
    {
      "space": "tree_hierarchy",
      "budget": "low",
      "budget_frac": 0.1,
      "seed": 10,
      "n_refined": 1.0,
      "n_passed": 1.0,
      "n_rejected": 0.0,
      "reject_rate": 0.0,
      "psnr_gain": 1.453185910136357,
      "compliance": 1.0,
      "topo_eta_f": 0.0,
      "topo_computation_ms": 0.0
    },
    {
      "space": "tree_hierarchy",
      "budget": "low",
      "budget_frac": 0.1,
      "seed": 11,
      "n_refined": 1.0,
      "n_passed": 1.0,
      "n_rejected": 0.0,
      "reject_rate": 0.0,
      "psnr_gain": 1.2381739943192454,
      "compliance": 1.0,
      "topo_eta_f": 0.0,
      "topo_computation_ms": 0.0
    },
    {
      "space": "tree_hierarchy",
      "budget": "low",
      "budget_frac": 0.1,
      "seed": 12,
      "n_refined": 1.0,
      "n_passed": 1.0,
      "n_rejected": 0.0,
      "reject_rate": 0.0,
      "psnr_gain": 1.2652504269518943,
      "compliance": 1.0,
      "topo_eta_f": 0.0,
      "topo_computation_ms": 0.0
    },
    {
      "space": "tree_hierarchy",
      "budget": "low",
      "budget_frac": 0.1,
      "seed": 13,
      "n_refined": 1.0,
      "n_passed": 1.0,
      "n_rejected": 0.0,
      "reject_rate": 0.0,
      "psnr_gain": 1.29406602579488,
      "compliance": 1.0,
      "topo_eta_f": 0.0,
      "topo_computation_ms": 0.0
    },
    {
      "space": "tree_hierarchy",
      "budget": "low",
      "budget_frac": 0.1,
      "seed": 14,
      "n_refined": 1.0,
      "n_passed": 1.0,
      "n_rejected": 0.0,
      "reject_rate": 0.0,
      "psnr_gain": 1.311669608221317,
      "compliance": 1.0,
      "topo_eta_f": 0.0,
      "topo_computation_ms": 0.0
    },
    {
      "space": "tree_hierarchy",
      "budget": "low",
      "budget_frac": 0.1,
      "seed": 15,
      "n_refined": 1.0,
      "n_passed": 1.0,
      "n_rejected": 0.0,
      "reject_rate": 0.0,
      "psnr_gain": 1.2337003866227807,
      "compliance": 1.0,
      "topo_eta_f": 0.0,
      "topo_computation_ms": 0.0
    },
    {
      "space": "tree_hierarchy",
      "budget": "low",
      "budget_frac": 0.1,
      "seed": 16,
      "n_refined": 1.0,
      "n_passed": 1.0,
      "n_rejected": 0.0,
      "reject_rate": 0.0,
      "psnr_gain": 1.1550955122286553,
      "compliance": 1.0,
      "topo_eta_f": 0.0,
      "topo_computation_ms": 0.0
    },
    {
      "space": "tree_hierarchy",
      "budget": "low",
      "budget_frac": 0.1,
      "seed": 17,
      "n_refined": 1.0,
      "n_passed": 1.0,
      "n_rejected": 0.0,
      "reject_rate": 0.0,
      "psnr_gain": 1.626293645735176,
      "compliance": 1.0,
      "topo_eta_f": 0.0,
      "topo_computation_ms": 0.0
    },
    {
      "space": "tree_hierarchy",
      "budget": "low",
      "budget_frac": 0.1,
      "seed": 18,
      "n_refined": 1.0,
      "n_passed": 1.0,
      "n_rejected": 0.0,
      "reject_rate": 0.0,
      "psnr_gain": 1.4785737363617688,
      "compliance": 1.0,
      "topo_eta_f": 0.0,
      "topo_computation_ms": 0.0
    },
    {
      "space": "tree_hierarchy",
      "budget": "low",
      "budget_frac": 0.1,
      "seed": 19,
      "n_refined": 1.0,
      "n_passed": 1.0,
      "n_rejected": 0.0,
      "reject_rate": 0.0,
      "psnr_gain": 1.0285441641498334,
      "compliance": 1.0,
      "topo_eta_f": 0.0,
      "topo_computation_ms": 0.0
    },
    {
      "space": "tree_hierarchy",
      "budget": "high",
      "budget_frac": 0.3,
      "seed": 0,
      "n_refined": 2.0,
      "n_passed": 2.0,
      "n_rejected": 0.0,
      "reject_rate": 0.0,
      "psnr_gain": 2.052427552310375,
      "compliance": 1.0,
      "topo_eta_f": 0.0,
      "topo_computation_ms": 0.0
    },
    {
      "space": "tree_hierarchy",
      "budget": "high",
      "budget_frac": 0.3,
      "seed": 1,
      "n_refined": 2.0,
      "n_passed": 1.0,
      "n_rejected": 0.0,
      "reject_rate": 0.0,
      "psnr_gain": 2.33955570166224,
      "compliance": 1.0,
      "topo_eta_f": 0.0,
      "topo_computation_ms": 0.0
    },
    {
      "space": "tree_hierarchy",
      "budget": "high",
      "budget_frac": 0.3,
      "seed": 2,
      "n_refined": 2.0,
      "n_passed": 1.0,
      "n_rejected": 0.0,
      "reject_rate": 0.0,
      "psnr_gain": 1.9283830207161454,
      "compliance": 1.0,
      "topo_eta_f": 0.0,
      "topo_computation_ms": 0.0
    },
    {
      "space": "tree_hierarchy",
      "budget": "high",
      "budget_frac": 0.3,
      "seed": 3,
      "n_refined": 2.0,
      "n_passed": 1.0,
      "n_rejected": 0.0,
      "reject_rate": 0.0,
      "psnr_gain": 2.107731608227004,
      "compliance": 1.0,
      "topo_eta_f": 0.0,
      "topo_computation_ms": 0.0
    },
    {
      "space": "tree_hierarchy",
      "budget": "high",
      "budget_frac": 0.3,
      "seed": 4,
      "n_refined": 2.0,
      "n_passed": 2.0,
      "n_rejected": 0.0,
      "reject_rate": 0.0,
      "psnr_gain": 2.26939167027583,
      "compliance": 1.0,
      "topo_eta_f": 0.0,
      "topo_computation_ms": 0.0
    },
    {
      "space": "tree_hierarchy",
      "budget": "high",
      "budget_frac": 0.3,
      "seed": 5,
      "n_refined": 2.0,
      "n_passed": 2.0,
      "n_rejected": 0.0,
      "reject_rate": 0.0,
      "psnr_gain": 2.0712572136483303,
      "compliance": 1.0,
      "topo_eta_f": 0.0,
      "topo_computation_ms": 0.0
    },
    {
      "space": "tree_hierarchy",
      "budget": "high",
      "budget_frac": 0.3,
      "seed": 6,
      "n_refined": 2.0,
      "n_passed": 1.0,
      "n_rejected": 0.0,
      "reject_rate": 0.0,
      "psnr_gain": 2.113157542154365,
      "compliance": 1.0,
      "topo_eta_f": 0.0,
      "topo_computation_ms": 0.0
    },
    {
      "space": "tree_hierarchy",
      "budget": "high",
      "budget_frac": 0.3,
      "seed": 7,
      "n_refined": 2.0,
      "n_passed": 1.0,
      "n_rejected": 0.0,
      "reject_rate": 0.0,
      "psnr_gain": 2.307496593653333,
      "compliance": 1.0,
      "topo_eta_f": 0.0,
      "topo_computation_ms": 0.0
    },
    {
      "space": "tree_hierarchy",
      "budget": "high",
      "budget_frac": 0.3,
      "seed": 8,
      "n_refined": 2.0,
      "n_passed": 2.0,
      "n_rejected": 0.0,
      "reject_rate": 0.0,
      "psnr_gain": 1.9715000355819985,
      "compliance": 1.0,
      "topo_eta_f": 0.0,
      "topo_computation_ms": 0.0
    },
    {
      "space": "tree_hierarchy",
      "budget": "high",
      "budget_frac": 0.3,
      "seed": 9,
      "n_refined": 2.0,
      "n_passed": 2.0,
      "n_rejected": 0.0,
      "reject_rate": 0.0,
      "psnr_gain": 2.3270130746543476,
      "compliance": 1.0,
      "topo_eta_f": 0.0,
      "topo_computation_ms": 0.0
    },
    {
      "space": "tree_hierarchy",
      "budget": "high",
      "budget_frac": 0.3,
      "seed": 10,
      "n_refined": 2.0,
      "n_passed": 2.0,
      "n_rejected": 0.0,
      "reject_rate": 0.0,
      "psnr_gain": 2.642686846242814,
      "compliance": 1.0,
      "topo_eta_f": 0.0,
      "topo_computation_ms": 0.0
    },
    {
      "space": "tree_hierarchy",
      "budget": "high",
      "budget_frac": 0.3,
      "seed": 11,
      "n_refined": 2.0,
      "n_passed": 1.0,
      "n_rejected": 0.0,
      "reject_rate": 0.0,
      "psnr_gain": 2.176654299810542,
      "compliance": 1.0,
      "topo_eta_f": 0.0,
      "topo_computation_ms": 0.0
    },
    {
      "space": "tree_hierarchy",
      "budget": "high",
      "budget_frac": 0.3,
      "seed": 12,
      "n_refined": 2.0,
      "n_passed": 1.0,
      "n_rejected": 0.0,
      "reject_rate": 0.0,
      "psnr_gain": 2.2252413139647356,
      "compliance": 1.0,
      "topo_eta_f": 0.0,
      "topo_computation_ms": 0.0
    },
    {
      "space": "tree_hierarchy",
      "budget": "high",
      "budget_frac": 0.3,
      "seed": 13,
      "n_refined": 2.0,
      "n_passed": 1.0,
      "n_rejected": 0.0,
      "reject_rate": 0.0,
      "psnr_gain": 2.280487364290254,
      "compliance": 1.0,
      "topo_eta_f": 0.0,
      "topo_computation_ms": 0.0
    },
    {
      "space": "tree_hierarchy",
      "budget": "high",
      "budget_frac": 0.3,
      "seed": 14,
      "n_refined": 2.0,
      "n_passed": 2.0,
      "n_rejected": 0.0,
      "reject_rate": 0.0,
      "psnr_gain": 2.3293785079200777,
      "compliance": 1.0,
      "topo_eta_f": 0.0,
      "topo_computation_ms": 0.0
    },
    {
      "space": "tree_hierarchy",
      "budget": "high",
      "budget_frac": 0.3,
      "seed": 15,
      "n_refined": 2.0,
      "n_passed": 2.0,
      "n_rejected": 0.0,
      "reject_rate": 0.0,
      "psnr_gain": 2.196398711507914,
      "compliance": 1.0,
      "topo_eta_f": 0.0,
      "topo_computation_ms": 0.0
    },
    {
      "space": "tree_hierarchy",
      "budget": "high",
      "budget_frac": 0.3,
      "seed": 16,
      "n_refined": 2.0,
      "n_passed": 2.0,
      "n_rejected": 0.0,
      "reject_rate": 0.0,
      "psnr_gain": 2.137069247991489,
      "compliance": 1.0,
      "topo_eta_f": 0.0,
      "topo_computation_ms": 0.0
    },
    {
      "space": "tree_hierarchy",
      "budget": "high",
      "budget_frac": 0.3,
      "seed": 17,
      "n_refined": 2.0,
      "n_passed": 1.0,
      "n_rejected": 0.0,
      "reject_rate": 0.0,
      "psnr_gain": 2.7297615838116247,
      "compliance": 1.0,
      "topo_eta_f": 0.0,
      "topo_computation_ms": 0.0
    },
    {
      "space": "tree_hierarchy",
      "budget": "high",
      "budget_frac": 0.3,
      "seed": 18,
      "n_refined": 2.0,
      "n_passed": 1.0,
      "n_rejected": 0.0,
      "reject_rate": 0.0,
      "psnr_gain": 2.499478651218327,
      "compliance": 1.0,
      "topo_eta_f": 0.0,
      "topo_computation_ms": 0.0
    },
    {
      "space": "tree_hierarchy",
      "budget": "high",
      "budget_frac": 0.3,
      "seed": 19,
      "n_refined": 2.0,
      "n_passed": 1.0,
      "n_rejected": 0.0,
      "reject_rate": 0.0,
      "psnr_gain": 2.0283927579483905,
      "compliance": 1.0,
      "topo_eta_f": 0.0,
      "topo_computation_ms": 0.0
    }
  ]
}